LICENSE
MANIFEST.in
README.rst
setup.py
compoundfiles/__init__.py
compoundfiles/const.py
compoundfiles/entities.py
compoundfiles/errors.py
compoundfiles/mmap.py
compoundfiles/reader.py
compoundfiles/streams.py
compoundfiles.egg-info/PKG-INFO
compoundfiles.egg-info/SOURCES.txt
compoundfiles.egg-info/dependency_links.txt
compoundfiles.egg-info/requires.txt
compoundfiles.egg-info/top_level.txt