Metadata-Version: 1.1
Name: compoundfiles
Version: 0.3
Summary: Library for parsing and reading OLE Compound Documents
Home-page: https://compound-files.readthedocs.org/
Author: Dave Hughes
Author-email: dave@waveform.org.uk
License: MIT License
Keywords: microsoft,ole,compound,document
Platform: A
Platform: L
Platform: L
Classifier: Development Status :: 4 - Beta
Classifier: Intended Audience :: Developers
Classifier: License :: OSI Approved :: MIT License
Classifier: Operating System :: Unix
Classifier: Operating System :: Microsoft :: Windows
Classifier: Programming Language :: Python :: 2.7
Classifier: Programming Language :: Python :: 3
